retrobus_perfetto/__init__.py
retrobus_perfetto/__init__.pyi
retrobus_perfetto/_build.py
retrobus_perfetto/annotations.py
retrobus_perfetto/builder.py
retrobus_perfetto/interning.py
retrobus_perfetto/perfetto_pb2.pyi
retrobus_perfetto/py.typed
retrobus_perfetto/reader.py
retrobus_perfetto/proto/__init__.py
retrobus_perfetto/proto/perfetto_pb2.py
retrobus_perfetto-0.3.0.dist-info/METADATA
retrobus_perfetto-0.3.0.dist-info/WHEEL
retrobus_perfetto-0.3.0.dist-info/top_level.txt
retrobus_perfetto-0.3.0.dist-info/RECORD
